datapizza/clients/openai_like/__init__.py
datapizza/clients/openai_like/memory_adapter.py
datapizza/clients/openai_like/openai_completion_client.py
datapizza_ai_clients_openai_like-0.0.6.dist-info/METADATA
datapizza_ai_clients_openai_like-0.0.6.dist-info/WHEEL
datapizza_ai_clients_openai_like-0.0.6.dist-info/RECORD
