Metadata-Version: 2.4
Name: datapizza-ai-clients-openai-like
Version: 0.0.6
Summary: OpenAI client for the datapizza-ai framework
Author-email: Datapizza <datapizza@datapizza.tech>
License: MIT
Classifier: License :: OSI Approved :: MIT License
Classifier: Operating System :: OS Independent
Classifier: Programming Language :: Python :: 3
Requires-Python: <4,>=3.10.0
Requires-Dist: datapizza-ai-core<0.1.0,>=0.0.5
Requires-Dist: httpx>=0.28.1
Requires-Dist: openai<3.0.0,>=2.0.0
